{
    "anims": [
        {
            "key": "left",
            "type": "frame",
            "frames": [
                {
                    "key": "center",
                    "duration": 0,
                    "keyframe": false
                },
                {
                    "key": "left1",
                    "duration": 0,
                    "keyframe": false
                },
                {
                    "key": "left2",
                    "duration": 0,
                    "keyframe": false
                }
            ],
            "frameRate": 24,
            "skipMissedFrames": true
        },
        {
            "key": "right",
            "type": "frame",
            "frames": [
                {
                    "key": "center",
                    "duration": 0,
                    "keyframe": false
                },
                {
                    "key": "right1",
                    "duration": 0,
                    "keyframe": false
                },
                {
                    "key": "right2",
                    "duration": 0,
                    "keyframe": false
                }
            ],
            "frameRate": 24,
            "skipMissedFrames": true
        },
        {
            "key": "up",
            "type": "frame",
            "frames": [
                {
                    "key": "center",
                    "duration": 0,
                    "keyframe": false
                },
                {
                    "key": "Up1",
                    "duration": 0,
                    "keyframe": false
                },
                {
                    "key": "Up2",
                    "duration": 0,
                    "keyframe": false
                }
            ],
            "frameRate": 16,
            "skipMissedFrames": true
        },
        {
            "key": "return",
            "type": "frame",
            "frames": [
                {
                    "key": "Up2",
                    "duration": 0,
                    "keyframe": false
                },
                {
                    "key": "Up1",
                    "duration": 0,
                    "keyframe": false
                },
                {
                    "key": "center",
                    "duration": 0,
                    "keyframe": false
                }
            ],
            "frameRate": 3,
            "skipMissedFrames": true
        }
    ],
    "globalTimeScale": 1,
    "meta": {
        "app": "Phaser Editor 2D v3",
        "contentType": "Phaser v3 Animations"
    }
}