{
    "anims": [
        {
            "key": "nave-black-explotionPlayer",
            "type": "frame",
            "frames": [
                {
                    "key": "PlayerE0",
                    "duration": 0,
                    "keyframe": false
                },
                {
                    "key": "PlayerE1",
                    "duration": 0,
                    "keyframe": false
                },
                {
                    "key": "PlayerE2",
                    "duration": 0,
                    "keyframe": false
                },
                {
                    "key": "PlayerE3",
                    "duration": 0,
                    "keyframe": false
                }
            ],
            "frameRate": 8,
            "skipMissedFrames": true
        }
    ],
    "globalTimeScale": 1,
    "meta": {
        "app": "Phaser Editor 2D v3",
        "contentType": "Phaser v3 Animations"
    }
}